<interface>
	<name>Get Association Statistics (Indexed)</name>
	<oid_index>.1.3.6.1.2.1.197.1.3.1.1.1</oid_index>
	<index_order>ntpAssocName:ntpAssocIndex</index_order>
	<index_order_type>numeric</index_order_type>
	<index_title_format>|chosen_order_field|</index_title_format>

	<fields>
		<ntpAssocIndex>
			<name>Index</name>
			<method>walk</method>
			<source>value</source>
			<direction>input</direction>
			<oid>.1.3.6.1.2.1.197.1.3.1.1.1</oid>
		</ntpAssocIndex>
		<ntpAssocName>
			<name>Name</name>
			<method>walk</method>
			<source>value</source>
			<direction>input</direction>
			<oid>.1.3.6.1.2.1.197.1.3.1.1.2</oid>
		</ntpAssocName>
		<ntpAssocRefId>
			<name>RefId</name>
			<method>walk</method>
			<source>value</source>
			<direction>input</direction>
			<oid>.1.3.6.1.2.1.197.1.3.1.1.3</oid>
		</ntpAssocRefId>
		<ntpAssocAddressType>
			<name>AddressType</name>
			<method>walk</method>
			<source>value</source>
			<direction>input</direction>
			<oid>.1.3.6.1.2.1.197.1.3.1.1.4</oid>
		</ntpAssocAddressType>
		<ntpAssocAddress>
			<name>Address</name>
			<method>walk</method>
			<source>value</source>
			<direction>input</direction>
			<oid>.1.3.6.1.2.1.197.1.3.1.1.5</oid>
		</ntpAssocAddress>
		<ntpAssocStratum>
			<name>Stratum</name>
			<method>walk</method>
			<source>value</source>
			<direction>output</direction>
			<oid>.1.3.6.1.2.1.197.1.3.1.1.7</oid>
		</ntpAssocStratum>
		<ntpAssocStatusJitter>
			<name>Jitter</name>
			<method>walk</method>
			<source>value</source>
			<direction>output</direction>
			<oid>.1.3.6.1.2.1.197.1.3.1.1.8</oid>
		</ntpAssocStatusJitter>
		<ntpAssocStatusDelay>
			<name>Delay</name>
			<method>walk</method>
			<source>value</source>
			<direction>output</direction>
			<oid>.1.3.6.1.2.1.197.1.3.1.1.9</oid>
		</ntpAssocStatusDelay>
		<ntpAssocStatusDispersion>
			<name>Dispersion</name>
			<method>walk</method>
			<source>value</source>
			<direction>output</direction>
			<oid>.1.3.6.1.2.1.197.1.3.1.1.10</oid>
		</ntpAssocStatusDispersion>
	</fields>
</interface>
